aeratable/__init__.py
aeratable/__main__.py
aeratable/__version__.py
aeratable/cli.py
aeratable-0.2.1.dist-info/LICENSE
aeratable-0.2.1.dist-info/METADATA
aeratable-0.2.1.dist-info/WHEEL
aeratable-0.2.1.dist-info/entry_points.txt
aeratable-0.2.1.dist-info/top_level.txt
aeratable-0.2.1.dist-info/RECORD
