Metadata-Version: 2.1
Name: aeratable
Version: 0.2.1
Summary: Nicely format Aera interface-output to a table in ASCII or CSV format.
Home-page: https://github.com/timolesterhuis/jrnlsync/
Author: Timo Lesterhuis
Author-email: timolesterhuis@gmail.com
License: MIT License
Project-URL: Source, https://github.com/timolesterhuis/aeratable
Project-URL: Issue Tracker, https://github.com/timolesterhuis/aeratable/issues
Classifier: Programming Language :: Python :: 3 :: Only
Classifier: Programming Language :: Python :: 3.5
Classifier: Programming Language :: Python :: 3.6
Classifier: Programming Language :: Python :: 3.7
Classifier: Programming Language :: Python :: 3.8
Classifier: Programming Language :: Python :: 3.9
Classifier: Programming Language :: Python :: 3.10
Classifier: Programming Language :: Python :: 3.11
Classifier: License :: OSI Approved :: MIT License
Classifier: Operating System :: OS Independent
License-File: LICENSE
Requires-Dist: pyperclip
Requires-Dist: tabulate
Requires-Dist: click
